twgy/__init__.py
twgy/cli.py
twgy/phonetic_reranker.py
twgy/analyzers/__init__.py
twgy/analyzers/finals_analyzer.py
twgy/analyzers/tone_analyzer.py
twgy/api/__init__.py
twgy/comparison/__init__.py
twgy/comparison/strategies.py
twgy/core/__init__.py
twgy/core/config.py
twgy/core/constants.py
twgy/core/exceptions.py
twgy/core/phonetic_classifier.py
twgy/core/phonetic_system.py
twgy/data/__init__.py
twgy/data/super_dictionary_manager.py
twgy/data/training_data_logger.py
twgy/data/super_dicts/super_dict_combined.json
twgy/data/super_dicts/super_dict_reversed.json
twgy/filters/__init__.py
twgy/filters/l1_consonant_filter.py
twgy/filters/l1_consonant_filter_optimized.py
twgy/filters/l2_first_last_reranker.py
twgy/filters/l2_first_last_reranker_optimized.py
twgy/filters/l3_full_phonetic_reranker.py
twgy/future/hybrid_phonetic_reranker.py
twgy/phonetic/__init__.py
twgy/phonetic/classifier.py
twgy/rerankers/__init__.py
twgy/rerankers/dimsim_reranker.py
twgy/similarity/__init__.py
twgy/similarity/engine.py
twgy/utils/__init__.py
twgy/utils/caching.py
twgy/utils/helpers.py
twgy-3.0.0.dist-info/METADATA
twgy-3.0.0.dist-info/WHEEL
twgy-3.0.0.dist-info/entry_points.txt
twgy-3.0.0.dist-info/top_level.txt
twgy-3.0.0.dist-info/RECORD
