Metadata-Version: 2.4
Name: twgy
Version: 3.0.0
Summary: Taiwan Mandarin Phonetic Similarity Processor - 台灣國語語音相似性處理系統
Home-page: https://github.com/yourusername/twgy
Author: TWGY Development Team
Author-email: TWGY Development Team <twgy.dev@example.com>
License: MIT
Project-URL: Homepage, https://github.com/twgy-team/twgy-v3
Project-URL: Repository, https://github.com/twgy-team/twgy-v3.git
Project-URL: Documentation, https://twgy-v3.readthedocs.io/
Project-URL: Bug Tracker, https://github.com/twgy-team/twgy-v3/issues
Classifier: Development Status :: 4 - Beta
Classifier: Intended Audience :: Developers
Classifier: Intended Audience :: Science/Research
Classifier: License :: OSI Approved :: MIT License
Classifier: Programming Language :: Python :: 3
Classifier: Programming Language :: Python :: 3.8
Classifier: Programming Language :: Python :: 3.9
Classifier: Programming Language :: Python :: 3.10
Classifier: Programming Language :: Python :: 3.11
Classifier: Topic :: Scientific/Engineering :: Artificial Intelligence
Classifier: Topic :: Text Processing :: Linguistic
Requires-Python: >=3.8
Requires-Dist: numpy>=1.20.0
Requires-Dist: pandas>=1.3.0
Requires-Dist: pypinyin>=0.44.0
Requires-Dist: dimsim>=0.2.0
Requires-Dist: tqdm>=4.60.0
Requires-Dist: scikit-learn>=1.0.0
Requires-Dist: requests>=2.25.0
Requires-Dist: pyyaml>=5.4.0
Provides-Extra: dev
Requires-Dist: pytest>=6.0; extra == "dev"
Requires-Dist: pytest-cov>=2.0; extra == "dev"
Requires-Dist: black>=21.0; extra == "dev"
Requires-Dist: flake8>=3.8; extra == "dev"
Requires-Dist: mypy>=0.812; extra == "dev"
Requires-Dist: jupyter>=1.0; extra == "dev"
Provides-Extra: full
Requires-Dist: sentence-transformers>=2.0; extra == "full"
Requires-Dist: faiss-cpu>=1.7.0; extra == "full"
Requires-Dist: torch>=1.9.0; extra == "full"
Provides-Extra: api
Requires-Dist: fastapi>=0.68.0; extra == "api"
Requires-Dist: uvicorn>=0.15.0; extra == "api"
Requires-Dist: pydantic>=1.8.0; extra == "api"
Dynamic: author
Dynamic: home-page
Dynamic: requires-python
